hypua2jamo/__init__.py
hypua2jamo/_cffi.abi3.so
hypua2jamo/_cython.cpython-38-darwin.so
hypua2jamo/c2d.bin
hypua2jamo/cli.py
hypua2jamo/d2c.bin
hypua2jamo/decoder.py
hypua2jamo/encoder.py
hypua2jamo/jc2p.bin
hypua2jamo/jd2p.bin
hypua2jamo/p2jc.bin
hypua2jamo/p2jd.bin
hypua2jamo-0.7.dist-info/COPYING
hypua2jamo-0.7.dist-info/COPYING.LESSER
hypua2jamo-0.7.dist-info/METADATA
hypua2jamo-0.7.dist-info/WHEEL
hypua2jamo-0.7.dist-info/entry_points.txt
hypua2jamo-0.7.dist-info/top_level.txt
hypua2jamo-0.7.dist-info/RECORD
