Metadata-Version: 2.1
Name: hypua2jamo
Version: 0.7
Summary: Convert Hanyang-PUA code to unicode Hangul Jamo, i.e., Syllable-Initial-Peak-Final Encoding (첫가끝 코드).
Home-page: https://github.com/mete0r/hypua2jamo
Author: mete0r
Author-email: 137794+mete0r@users.noreply.github.com
License: GNU Lesser General Public License v3 or later (LGPLv3+)
Keywords: Hanyang,PUA,Unicode,Syllable-Initial-Peak-Final Encoding
Classifier: Development Status :: 5 - Production/Stable
Classifier: Intended Audience :: Developers
Classifier: License :: OSI Approved :: GNU Lesser General Public License v3 or later (LGPLv3+)
Classifier: Natural Language :: Korean
Classifier: Operating System :: OS Independent
Classifier: Programming Language :: Python :: 2.7
Classifier: Programming Language :: Python :: 3.7
Classifier: Programming Language :: Python :: 3.8
Classifier: Programming Language :: Python :: 3.9
Classifier: Programming Language :: Python :: 3.10
Classifier: Programming Language :: Python :: 3.11
Classifier: Programming Language :: Python :: Implementation :: CPython
Classifier: Topic :: Text Processing :: Filters
Requires-Python: >=2.7, !=3.0.*, !=3.1.*, !=3.2.*, !=3.3.*, !=3.4.*, !=3.5.*,!=3.6.*
License-File: COPYING
License-File: COPYING.LESSER
Requires-Dist: cffi (>=1.0.0)
